MANIFEST.in
README.md
setup.py
simple_detection/__init__.py
simple_detection.egg-info/PKG-INFO
simple_detection.egg-info/SOURCES.txt
simple_detection.egg-info/dependency_links.txt
simple_detection.egg-info/top_level.txt
tests/__init__.py